pyrdt/__init__.py
pyrdt/atom.py
pyrdt/combo.py
pyrdt/math.py
pyrdt/stat.py
pyrdt-1.0.1.dist-info/LICENSE
pyrdt-1.0.1.dist-info/METADATA
pyrdt-1.0.1.dist-info/WHEEL
pyrdt-1.0.1.dist-info/top_level.txt
pyrdt-1.0.1.dist-info/RECORD
